odoo/addons/l10n_it_account_vat_period_end_settlement/README.rst
odoo/addons/l10n_it_account_vat_period_end_settlement/__init__.py
odoo/addons/l10n_it_account_vat_period_end_settlement/__manifest__.py
odoo/addons/l10n_it_account_vat_period_end_settlement/hooks.py
odoo/addons/l10n_it_account_vat_period_end_settlement/i18n/account_vat_period_end_statement.pot
odoo/addons/l10n_it_account_vat_period_end_settlement/i18n/am.po
odoo/addons/l10n_it_account_vat_period_end_settlement/i18n/ar.po
odoo/addons/l10n_it_account_vat_period_end_settlement/i18n/bg.po
odoo/addons/l10n_it_account_vat_period_end_settlement/i18n/bs.po
odoo/addons/l10n_it_account_vat_period_end_settlement/i18n/ca.po
odoo/addons/l10n_it_account_vat_period_end_settlement/i18n/ca_ES.po
odoo/addons/l10n_it_account_vat_period_end_settlement/i18n/cs.po
odoo/addons/l10n_it_account_vat_period_end_settlement/i18n/da.po
odoo/addons/l10n_it_account_vat_period_end_settlement/i18n/de.po
odoo/addons/l10n_it_account_vat_period_end_settlement/i18n/el_GR.po
odoo/addons/l10n_it_account_vat_period_end_settlement/i18n/en_AU.po
odoo/addons/l10n_it_account_vat_period_end_settlement/i18n/en_GB.po
odoo/addons/l10n_it_account_vat_period_end_settlement/i18n/es.po
odoo/addons/l10n_it_account_vat_period_end_settlement/i18n/es_AR.po
odoo/addons/l10n_it_account_vat_period_end_settlement/i18n/es_CL.po
odoo/addons/l10n_it_account_vat_period_end_settlement/i18n/es_CO.po
odoo/addons/l10n_it_account_vat_period_end_settlement/i18n/es_CR.po
odoo/addons/l10n_it_account_vat_period_end_settlement/i18n/es_DO.po
odoo/addons/l10n_it_account_vat_period_end_settlement/i18n/es_EC.po
odoo/addons/l10n_it_account_vat_period_end_settlement/i18n/es_ES.po
odoo/addons/l10n_it_account_vat_period_end_settlement/i18n/es_MX.po
odoo/addons/l10n_it_account_vat_period_end_settlement/i18n/es_PE.po
odoo/addons/l10n_it_account_vat_period_end_settlement/i18n/es_PY.po
odoo/addons/l10n_it_account_vat_period_end_settlement/i18n/es_VE.po
odoo_addon_l10n_it_account_vat_period_end_settlement-18.0.1.0.2.1.dist-info/METADATA
odoo_addon_l10n_it_account_vat_period_end_settlement-18.0.1.0.2.1.dist-info/WHEEL
odoo_addon_l10n_it_account_vat_period_end_settlement-18.0.1.0.2.1.dist-info/top_level.txt
odoo_addon_l10n_it_account_vat_period_end_settlement-18.0.1.0.2.1.dist-info/RECORD
