Metadata-Version: 2.1
Name: odoo-addon-l10n_it_account_vat_period_end_settlement
Version: 18.0.1.0.2.1
Requires-Python: >=3.10
Requires-Dist: odoo-addon-account_tax_balance==18.0.*
Requires-Dist: odoo-addon-date_range==18.0.*
Requires-Dist: odoo-addon-l10n_it_account==18.0.*
Requires-Dist: odoo==18.0.*
Requires-Dist: openupgradelib
Summary: Allow to create the 'VAT Settlement'.
Home-page: https://github.com/OCA/l10n-italy
License: AGPL-3
Author: Agile Business Group, Odoo Community Association (OCA), LinkIt Spa
Author-email: support@odoo-community.org
Classifier: Programming Language :: Python
Classifier: Framework :: Odoo
Classifier: Framework :: Odoo :: 18.0
Classifier: License :: OSI Approved :: GNU Affero General Public License v3
